README.md
setup.py
api_template/__init__.py
api_template/config.py
api_template/inmutables.py
cleandev_api_template.egg-info/PKG-INFO
cleandev_api_template.egg-info/SOURCES.txt
cleandev_api_template.egg-info/dependency_links.txt
cleandev_api_template.egg-info/requires.txt
cleandev_api_template.egg-info/top_level.txt