Metadata-Version: 2.1
Name: cleandev-api-template
Version: 0.2.2
Summary: Fachada para crear apis mas facilmente
Home-page: https://gitlab.com/cleansoftware/libs/public/cleandev-api-template
Author: Daniel Rodriguez Rodriguez
Author-email: danielrodriguezrodriguez.pks@gmail.com
License: UNKNOWN
Project-URL: Bug Tracker, https://gitlab.com/cleansoftware/libs/public/cleandev-api-template/-/issues
Platform: UNKNOWN
Classifier: Programming Language :: Python :: 3
Classifier: License :: OSI Approved :: MIT License
Classifier: Operating System :: OS Independent
Requires-Python: >=3.9
